pdbtools/__init__.py
pdbtools/pdb_b.py
pdbtools/pdb_chain.py
pdbtools/pdb_chainbows.py
pdbtools/pdb_chainxseg.py
pdbtools/pdb_chkensemble.py
pdbtools/pdb_delchain.py
pdbtools/pdb_delelem.py
pdbtools/pdb_delhetatm.py
pdbtools/pdb_delinsertion.py
pdbtools/pdb_delres.py
pdbtools/pdb_delresname.py
pdbtools/pdb_element.py
pdbtools/pdb_fetch.py
pdbtools/pdb_fixinsert.py
pdbtools/pdb_fromcif.py
pdbtools/pdb_gap.py
pdbtools/pdb_head.py
pdbtools/pdb_intersect.py
pdbtools/pdb_keepcoord.py
pdbtools/pdb_merge.py
pdbtools/pdb_mkensemble.py
pdbtools/pdb_occ.py
pdbtools/pdb_reatom.py
pdbtools/pdb_reres.py
pdbtools/pdb_rplchain.py
pdbtools/pdb_rplresname.py
pdbtools/pdb_seg.py
pdbtools/pdb_segxchain.py
pdbtools/pdb_selaltloc.py
pdbtools/pdb_selatom.py
pdbtools/pdb_selchain.py
pdbtools/pdb_selelem.py
pdbtools/pdb_selhetatm.py
pdbtools/pdb_selmodel.py
pdbtools/pdb_selres.py
pdbtools/pdb_selresname.py
pdbtools/pdb_selseg.py
pdbtools/pdb_shiftres.py
pdbtools/pdb_sort.py
pdbtools/pdb_splitchain.py
pdbtools/pdb_splitmodel.py
pdbtools/pdb_splitseg.py
pdbtools/pdb_tidy.py
pdbtools/pdb_tocif.py
pdbtools/pdb_tofasta.py
pdbtools/pdb_uniqname.py
pdbtools/pdb_validate.py
pdbtools/pdb_wc.py
tests/__init__.py
tests/config.py
tests/test_pdb_b.py
tests/test_pdb_chain.py
tests/test_pdb_chainbows.py
tests/test_pdb_chainxseg.py
tests/test_pdb_chkensemble.py
tests/test_pdb_delchain.py
tests/test_pdb_delelem.py
tests/test_pdb_delhetatm.py
tests/test_pdb_delinsertion.py
tests/test_pdb_delres.py
tests/test_pdb_delresname.py
tests/test_pdb_element.py
tests/test_pdb_fixinsert.py
tests/test_pdb_fromcif.py
tests/test_pdb_gap.py
tests/test_pdb_head.py
tests/test_pdb_intersect.py
tests/test_pdb_keepcoord.py
tests/test_pdb_merge.py
tests/test_pdb_mkensemble.py
tests/test_pdb_occ.py
tests/test_pdb_reatom.py
tests/test_pdb_reres.py
tests/test_pdb_rplchain.py
tests/test_pdb_rplresname.py
tests/test_pdb_seg.py
tests/test_pdb_segxchain.py
tests/test_pdb_selaltloc.py
tests/test_pdb_selatom.py
pdb_tools-2.5.0.dist-info/LICENSE
pdb_tools-2.5.0.dist-info/METADATA
pdb_tools-2.5.0.dist-info/WHEEL
pdb_tools-2.5.0.dist-info/entry_points.txt
pdb_tools-2.5.0.dist-info/top_level.txt
pdb_tools-2.5.0.dist-info/RECORD
